fastapi_exceptionshandler/__init__.py
fastapi_exceptionshandler/api_exception.py
fastapi_exceptionshandler/api_exception_handler.py
fastapi_exceptionshandler/api_exception_manager.py
fastapi_exceptionshandler/api_exception_middleware.py
fastapi_exceptionshandler-0.1.2.dist-info/METADATA
fastapi_exceptionshandler-0.1.2.dist-info/WHEEL
fastapi_exceptionshandler-0.1.2.dist-info/top_level.txt
fastapi_exceptionshandler-0.1.2.dist-info/RECORD
