Metadata-Version: 2.1
Name: fastapi_exceptionshandler
Version: 0.1.2
Summary: Standardize and handle exceptions in FastAPI more elegantly
Author-email: SirPaulO <me@sirpauloliver.com>
License: MIT License
Project-URL: Homepage, https://github.com/SirPaulO/fastapi_exceptionshandler
Project-URL: Bug Tracker, https://github.com/SirPaulO/fastapi_exceptionshandler/issues
Project-URL: Repository, https://github.com/SirPaulO/fastapi_exceptionshandler.git
Keywords: fastapi,middleware,exception,error,handler,response,api
Classifier: Programming Language :: Python :: 3
Classifier: License :: OSI Approved :: MIT License
Classifier: Operating System :: OS Independent
Requires-Python: >=3.7
Requires-Dist: fastapi>=0.95.2
